pyKobana/Kobana.py
pyKobana/__init__.py
pyKobana-0.0.4.dist-info/LICENSE
pyKobana-0.0.4.dist-info/METADATA
pyKobana-0.0.4.dist-info/WHEEL
pyKobana-0.0.4.dist-info/top_level.txt
pyKobana-0.0.4.dist-info/RECORD
