Metadata-Version: 2.2
Name: pyKobana
Version: 0.0.4
Summary: A Python client for the Elasticsearch REST API
Author-email: Dola Lima <dolalima@gmail.com>
Project-URL: Homepage, https://github.com/dolalima/pyKobana
Project-URL: Issues, https://github.com/dolalima/pyKobana/issues
Classifier: Development Status :: 3 - Alpha
Requires-Python: >=3.8
License-File: LICENSE
Requires-Dist: requests
